setup.cfg
setup.py
fi_ky225.egg-info/PKG-INFO
fi_ky225.egg-info/SOURCES.txt
fi_ky225.egg-info/dependency_links.txt
fi_ky225.egg-info/not-zip-safe
fi_ky225.egg-info/top_level.txt
fi_ky225/circle/__init__.py
fi_ky225/circle/code.py
fi_ky225/square/__init__.py
fi_ky225/square/code.py
fi_ky225/triangle/__init__.py
fi_ky225/triangle/code.py