Metadata-Version: 2.1
Name: fi-ky225
Version: 0.0
Summary: circle, tiangle, square
Author-email: yablochkinkirill95@gmail.com
